setup.py
TracEmailDigestPlugin.egg-info/PKG-INFO
TracEmailDigestPlugin.egg-info/SOURCES.txt
TracEmailDigestPlugin.egg-info/dependency_links.txt
TracEmailDigestPlugin.egg-info/entry_points.txt
TracEmailDigestPlugin.egg-info/not-zip-safe
TracEmailDigestPlugin.egg-info/requires.txt
TracEmailDigestPlugin.egg-info/top_level.txt
notifier/__init__.py
notifier/consumertask.py
notifier/notifier.py