Metadata-Version: 1.0
Name: TracEmailDigestPlugin
Version: 0.1
Summary: Email notifications & daily digests for tickets in Trac
Home-page: http://www.lshift.net/
Author: Lee Wei
Author-email: leewei@lshift.net
License: BSD
Download-URL: http://www.lshift.net/
Keywords: trac email digest plugin
Platform: UNKNOWN
Classifier: Intended Audience :: Developers
Classifier: License :: OSI Approved :: BSD License
Classifier: Operating System :: Unix
Classifier: Programming Language :: Python
Classifier: Topic :: Software Development :: Bug Tracking
Classifier: Topic :: Software Development :: Version Control
